semverlib/__init__.py
semverlib/semver.py
semverlib-1.0.0.dist-info/METADATA
semverlib-1.0.0.dist-info/WHEEL
semverlib-1.0.0.dist-info/licenses/LICENSE
semverlib-1.0.0.dist-info/RECORD
